devtools_base32/__init__.py
devtools_base32-1.0.1.dist-info/METADATA
devtools_base32-1.0.1.dist-info/WHEEL
devtools_base32-1.0.1.dist-info/top_level.txt
devtools_base32-1.0.1.dist-info/RECORD
