Metadata-Version: 2.1
Name: devtools-base32
Version: 1.0.1
Summary: Base32 encoder/decoder
Home-page: https://devtools.at/tools/base32
Author: DevTools.at
Author-email: hello@devtools.at
Project-URL: Homepage, https://devtools.at/tools/base32
Project-URL: Repository, https://github.com/devtools-at/base32
Classifier: Development Status :: 4 - Beta
Classifier: Intended Audience :: Developers
Classifier: License :: OSI Approved :: MIT License
Classifier: Programming Language :: Python :: 3
Requires-Python: >=3.8
